[
    {
        "uri": "http://www.w3.org/2002/07/owl#",
        "prefix": "owl"
    },
    {
        "uri": "http://www.w3.org/2000/01/rdf-schema#",
        "prefix": "rdfs"
    },
    {
        "uri": "http://www.w3.org/1999/02/22-rdf-syntax-ns#",
        "prefix": "ns"
    },
    {
        "uri": "http://www.w3.org/2004/02/skos/core#",
        "prefix": "skos"
    },
    {
        "uri": "http://xmlns.com/foaf/0.1/",
        "prefix": "foaf"
    },
    {
        "uri": "http://www.w3.org/2001/XMLSchema#",
        "prefix": "xsd"
    },
    {
        "uri": "http://deepomics.inrae.fr/",
        "prefix": "deepomics"
    }
]


